moviecli/__init__.py
moviecli/cli.py
moviecli/config.py
moviecli/test.py
moviecli/torrent_downloader.py
moviecli/utils.py
moviecli/ytswebs.py
moviecli-0.1.2.dist-info/METADATA
moviecli-0.1.2.dist-info/WHEEL
moviecli-0.1.2.dist-info/entry_points.txt
moviecli-0.1.2.dist-info/top_level.txt
moviecli-0.1.2.dist-info/RECORD
