Metadata-Version: 2.1
Name: moviecli
Version: 0.1.2
Summary: CLI tool for searching and downloading movies from yts
Home-page: https://github.com/yannickRafael/moviecli
Author: yannickRafael
Author-email: yannickrafael286@gmail.com
License: UNKNOWN
Platform: UNKNOWN
Classifier: Programming Language :: Python :: 3
Classifier: License :: OSI Approved :: MIT License
Classifier: Environment :: Console
Classifier: Intended Audience :: End Users/Desktop
Classifier: Topic :: Multimedia :: Video
Classifier: Topic :: Utilities
Requires-Python: >=3.8
Requires-Dist: click
Requires-Dist: InquirerPy
Requires-Dist: torrentp
Requires-Dist: beautifulsoup4
Requires-Dist: requests
